easy_googlesheets
