Metadata-Version: 2.1
Name: easy-googlesheets
Version: 0.1.5
Summary: Google sheets API, easy to use
Home-page: https://github.com/RoberWare/easy_googlesheets
Author: Roberto Lama Rodriguez
Author-email: roberlama@gmail.com
License: MIT
Keywords: api,google,easy,sheets,database,googlesheets,free
Platform: UNKNOWN
Classifier: Development Status :: 3 - Alpha
Classifier: Intended Audience :: Developers
Classifier: Topic :: Software Development :: Build Tools
Classifier: License :: OSI Approved :: MIT License
Classifier: Programming Language :: Python :: 3
Classifier: Programming Language :: Python :: 3.4
Classifier: Programming Language :: Python :: 3.5
Classifier: Programming Language :: Python :: 3.6
